mongodb_orm/__init__.py
mongodb_orm/apps.py
mongodb_orm/urls.py
mongodb_orm/custom_urls/__init__.py
mongodb_orm/custom_urls/bread_urls.py
mongodb_orm/decorators/__init__.py
mongodb_orm/decorators/chained.py
mongodb_orm/exceptions/__init__.py
mongodb_orm/exceptions/syntax_exceptions.py
mongodb_orm/interfaces/__init__.py
mongodb_orm/interfaces/base_mongodb_model.py
mongodb_orm/interfaces/mongodb_model.py
mongodb_orm/interfaces/mongodb_model_events.py
mongodb_orm/management/__init__.py
mongodb_orm/management/commands/__init__.py
mongodb_orm/management/commands/update_schema.py
mongodb_orm/models/__init__.py
mongodb_orm/models/generic_model.py
mongodb_orm/singletons/__init__.py
mongodb_orm/singletons/mongodb_singleton_client.py
mongodb_orm/types/Relation.py
mongodb_orm/types/__init__.py
mongodb_orm/types/index.py
mongodb_orm/types/logger_object.py
mongodb_orm/types/model_schema.py
mongodb_orm/types/options.py
mongodb_orm/utils/__init__.py
mongodb_orm/utils/helpers.py
mongodb_orm/views/__init__.py
mongodb_orm/views/mongodb_api_model_view.py
mongodb_orm-0.1.12.dist-info/METADATA
mongodb_orm-0.1.12.dist-info/WHEEL
mongodb_orm-0.1.12.dist-info/top_level.txt
mongodb_orm-0.1.12.dist-info/RECORD
