Metadata-Version: 2.1
Name: mongodb_orm
Version: 0.1.12
Summary: mongodb ORM for django framework
Author: Khai
Author-email: sarraj.khaireddine@gmail.com
License: MIT
Classifier: License :: OSI Approved :: MIT License
Requires-Dist: django
Requires-Dist: djangorestframework
Requires-Dist: pymongo
